[{"iob":-0.414,"activity":0.0015,"bolussnooze":0,"basaliob":-0.526,"netbasalinsulin":-0.1,"hightempinsulin":0.7,"time":"2016-08-03T23:56:41.000Z"},{"iob":-0.466,"activity":0.0004,"bolussnooze":0,"basaliob":-0.556,"netbasalinsulin":-0.2,"hightempinsulin":0.65,"time":"2016-08-04T00:01:41.000Z"},{"iob":-0.513,"activity":-0.0007,"bolussnooze":0,"basaliob":-0.582,"netbasalinsulin":-0.25,"hightempinsulin":0.65,"time":"2016-08-04T00:06:41.000Z"},{"iob":-0.554,"activity":-0.0018,"bolussnooze":0,"basaliob":-0.607,"netbasalinsulin":-0.4,"hightempinsulin":0.55,"time":"2016-08-04T00:11:41.000Z"},{"iob":-0.59,"activity":-0.0028,"bolussnooze":0,"basaliob":-0.628,"netbasalinsulin":-0.5,"hightempinsulin":0.5,"time":"2016-08-04T00:16:41.000Z"},{"iob":-0.571,"activity":-0.0037,"bolussnooze":0,"basaliob":-0.597,"netbasalinsulin":-0.6,"hightempinsulin":0.4,"time":"2016-08-04T00:21:41.000Z"},{"iob":-0.548,"activity":-0.0046,"bolussnooze":0,"basaliob":-0.564,"netbasalinsulin":-0.65,"hightempinsulin":0.35,"time":"2016-08-04T00:26:41.000Z"},{"iob":-0.521,"activity":-0.0053,"bolussnooze":0,"basaliob":-0.53,"netbasalinsulin":-0.75,"hightempinsulin":0.25,"time":"2016-08-04T00:31:41.000Z"},{"iob":-0.491,"activity":-0.006,"bolussnooze":0,"basaliob":-0.495,"netbasalinsulin":-0.8,"hightempinsulin":0.2,"time":"2016-08-04T00:36:41.000Z"},{"iob":-0.459,"activity":-0.0065,"bolussnooze":0,"basaliob":-0.459,"netbasalinsulin":-0.9,"hightempinsulin":0.1,"time":"2016-08-04T00:41:41.000Z"},{"iob":-0.424,"activity":-0.0069,"bolussnooze":0,"basaliob":-0.424,"netbasalinsulin":-0.95,"hightempinsulin":0.05,"time":"2016-08-04T00:46:41.000Z"},{"iob":-0.39,"activity":-0.0069,"bolussnooze":0,"basaliob":-0.39,"netbasalinsulin":-1,"hightempinsulin":0,"time":"2016-08-04T00:51:41.000Z"},{"iob":-0.356,"activity":-0.0067,"bolussnooze":0,"basaliob":-0.356,"netbasalinsulin":-1,"hightempinsulin":0,"time":"2016-08-04T00:56:41.000Z"},{"iob":-0.323,"activity":-0.0066,"bolussnooze":0,"basaliob":-0.323,"netbasalinsulin":-1,"hightempinsulin":0,"time":"2016-08-04T01:01:41.000Z"},{"iob":-0.291,"activity":-0.0064,"bolussnooze":0,"basaliob":-0.291,"netbasalinsulin":-1,"hightempinsulin":0,"time":"2016-08-04T01:06:41.000Z"},{"iob":-0.261,"activity":-0.0061,"bolussnooze":0,"basaliob":-0.261,"netbasalinsulin":-1,"hightempinsulin":0,"time":"2016-08-04T01:11:41.000Z"},{"iob":-0.232,"activity":-0.0058,"bolussnooze":0,"basaliob":-0.232,"netbasalinsulin":-0.95,"hightempinsulin":0,"time":"2016-08-04T01:16:41.000Z"},{"iob":-0.204,"activity":-0.0055,"bolussnooze":0,"basaliob":-0.204,"netbasalinsulin":-0.9,"hightempinsulin":0,"time":"2016-08-04T01:21:41.000Z"},{"iob":-0.179,"activity":-0.0051,"bolussnooze":0,"basaliob":-0.179,"netbasalinsulin":-0.85,"hightempinsulin":0,"time":"2016-08-04T01:26:41.000Z"},{"iob":-0.155,"activity":-0.0047,"bolussnooze":0,"basaliob":-0.155,"netbasalinsulin":-0.8,"hightempinsulin":0,"time":"2016-08-04T01:31:41.000Z"},{"iob":-0.134,"activity":-0.0043,"bolussnooze":0,"basaliob":-0.134,"netbasalinsulin":-0.75,"hightempinsulin":0,"time":"2016-08-04T01:36:41.000Z"},{"iob":-0.115,"activity":-0.0039,"bolussnooze":0,"basaliob":-0.115,"netbasalinsulin":-0.75,"hightempinsulin":0,"time":"2016-08-04T01:41:41.000Z"},{"iob":-0.098,"activity":-0.0035,"bolussnooze":0,"basaliob":-0.098,"netbasalinsulin":-0.7,"hightempinsulin":0,"time":"2016-08-04T01:46:41.000Z"},{"iob":-0.082,"activity":-0.0031,"bolussnooze":0,"basaliob":-0.082,"netbasalinsulin":-0.7,"hightempinsulin":0,"time":"2016-08-04T01:51:41.000Z"},{"iob":-0.068,"activity":-0.0028,"bolussnooze":0,"basaliob":-0.068,"netbasalinsulin":-0.65,"hightempinsulin":0,"time":"2016-08-04T01:56:41.000Z"},{"iob":-0.056,"activity":-0.0024,"bolussnooze":0,"basaliob":-0.056,"netbasalinsulin":-0.65,"hightempinsulin":0,"time":"2016-08-04T02:01:41.000Z"},{"iob":-0.046,"activity":-0.0021,"bolussnooze":0,"basaliob":-0.046,"netbasalinsulin":-0.6,"hightempinsulin":0,"time":"2016-08-04T02:06:41.000Z"},{"iob":-0.037,"activity":-0.0018,"bolussnooze":0,"basaliob":-0.037,"netbasalinsulin":-0.5,"hightempinsulin":0,"time":"2016-08-04T02:11:41.000Z"},{"iob":-0.029,"activity":-0.0015,"bolussnooze":0,"basaliob":-0.029,"netbasalinsulin":-0.45,"hightempinsulin":0,"time":"2016-08-04T02:16:41.000Z"},{"iob":-0.022,"activity":-0.0013,"bolussnooze":0,"basaliob":-0.022,"netbasalinsulin":-0.4,"hightempinsulin":0,"time":"2016-08-04T02:21:41.000Z"},{"iob":-0.017,"activity":-0.0011,"bolussnooze":0,"basaliob":-0.017,"netbasalinsulin":-0.35,"hightempinsulin":0,"time":"2016-08-04T02:26:41.000Z"},{"iob":-0.012,"activity":-0.0009,"bolussnooze":0,"basaliob":-0.012,"netbasalinsulin":-0.3,"hightempinsulin":0,"time":"2016-08-04T02:31:41.000Z"},{"iob":-0.008,"activity":-0.0008,"bolussnooze":0,"basaliob":-0.008,"netbasalinsulin":-0.3,"hightempinsulin":0,"time":"2016-08-04T02:36:41.000Z"},{"iob":-0.005,"activity":-0.0006,"bolussnooze":0,"basaliob":-0.005,"netbasalinsulin":-0.3,"hightempinsulin":0,"time":"2016-08-04T02:41:41.000Z"},{"iob":-0.003,"activity":-0.0004,"bolussnooze":0,"basaliob":-0.003,"netbasalinsulin":-0.3,"hightempinsulin":0,"time":"2016-08-04T02:46:41.000Z"},{"iob":-0.002,"activity":-0.0003,"bolussnooze":0,"basaliob":-0.002,"netbasalinsulin":-0.25,"hightempinsulin":0,"time":"2016-08-04T02:51:41.000Z"}]
