{
  "bg": 218, 
  "temp": "absolute", 
  "snoozeBG": 126, 
  "predBGs": {
    "COB": [
      218, 
      221, 
      223, 
      224, 
      225, 
      224, 
      223, 
      221, 
      218, 
      215, 
      211, 
      206, 
      201, 
      196, 
      190, 
      184, 
      179, 
      173, 
      167, 
      162, 
      158, 
      153, 
      149, 
      145, 
      142, 
      138, 
      136, 
      133, 
      130, 
      128, 
      127, 
      125, 
      124, 
      123, 
      123, 
      122
    ], 
    "aCOB": [
      218, 
      226, 
      232, 
      237, 
      241, 
      243, 
      243, 
      242, 
      240, 
      236, 
      231, 
      225, 
      218, 
      210, 
      202, 
      195, 
      187, 
      179, 
      172, 
      166, 
      160, 
      154, 
      149, 
      144, 
      140, 
      136, 
      133, 
      130, 
      128, 
      126, 
      124, 
      122, 
      121, 
      121, 
      120, 
      120, 
      119
    ], 
    "IOB": [
      218, 
      221, 
      222, 
      223, 
      223, 
      221, 
      219, 
      215, 
      211, 
      205, 
      199, 
      192, 
      185, 
      177, 
      169, 
      161, 
      153, 
      146, 
      139, 
      132, 
      126, 
      121, 
      115, 
      111, 
      107, 
      103, 
      100, 
      97, 
      94, 
      92, 
      90, 
      89, 
      88, 
      87, 
      86
    ]
  }, 
  "rate": 1.15, 
  "reason": "COB: 16, Dev: 26, BGI: -1.36, ISF: 78, Target: 107; Eventual BG 124 >= 107, 10m@2.550 = 0.425 > req 0.22+20%. Setting temp basal of 1.15U/hr", 
  "COB": 16, 
  "eventualBG": 124, 
  "duration": 30, 
  "tick": "+3", 
  "IOB": 1.552
}