[
  {
    "created_at": "2016-09-13T16:35:21.378Z", 
    "mmtune": {
      "scanDetails": [
        [
          "916.540", 
          5, 
          -72
        ], 
        [
          "916.564", 
          4, 
          -70
        ], 
        [
          "916.588", 
          5, 
          -66
        ], 
        [
          "916.612", 
          5, 
          -65
        ], 
        [
          "916.636", 
          5, 
          -59
        ], 
        [
          "916.660", 
          5, 
          -61
        ], 
        [
          "916.684", 
          5, 
          -71
        ]
      ], 
      "setFreq": 916.636, 
      "usedDefault": false, 
      "timestamp": "2016-09-13T16:33:00.000Z"
    }, 
    "pump": {
      "battery": {
        "status": "normal", 
        "voltage": 1.35
      }, 
      "status": {
        "status": "normal", 
        "timestamp": "2016-09-13T16:33:24.000Z", 
        "bolusing": false, 
        "suspended": false
      }, 
      "reservoir": 98.05, 
      "clock": "2016-09-13T09:33:26-07:00"
    }, 
    "openaps": {
      "suggested": {
        "bg": 126, 
        "temp": "absolute", 
        "snoozeBG": 58, 
        "timestamp": "2016-09-13T16:35:12.000Z", 
        "predBGs": {
          "IOB": [
            126, 
            116, 
            106, 
            98, 
            90, 
            84, 
            78, 
            74, 
            70, 
            67, 
            64, 
            63, 
            62, 
            62, 
            61, 
            61, 
            60, 
            60, 
            60, 
            60, 
            60, 
            61, 
            61, 
            61, 
            62, 
            62, 
            62, 
            63, 
            63, 
            63, 
            64, 
            64, 
            65, 
            65, 
            65, 
            65, 
            65, 
            66
          ]
        }, 
        "reason": "COB: 0, Dev: -44, BGI: -1.74, ISF: 85, Target: 112; Eventual BG 58 < 112, setting -1.975U/hr, but 27m left and 0 ~ req 0U/hr: no action required", 
        "COB": 0, 
        "eventualBG": 58, 
        "tick": -11, 
        "IOB": 0.288
      }, 
      "iob": {
        "netbasalinsulin": 0.6, 
        "timestamp": "2016-09-13T16:33:26.000Z", 
        "activity": 0.0041, 
        "basaliob": 0.27, 
        "hightempinsulin": 1.2, 
        "bolussnooze": 0, 
        "iob": 0.288
      }, 
      "enacted": {
        "bg": 137, 
        "temp": "absolute", 
        "snoozeBG": 91, 
        "recieved": true, 
        "reason": "COB: 0, Dev: -15, BGI: -1.86, ISF: 87, Target: 113; Eventual BG 91 < 113, setting -0.45U/hr", 
        "rate": 0, 
        "COB": 0, 
        "eventualBG": 91, 
        "timestamp": "2016-09-13T16:30:19.000Z", 
        "duration": 30, 
        "tick": -9, 
        "IOB": 0.359
      }
    }, 
    "uploader": {
      "battery": 74, 
      "batteryVoltage": 3923
    }, 
    "device": "openaps://indy-e1", 
    "_id": "57d82ac999318f896b06fbd5"
  }
]