{
  "bg": 135, 
  "temp": "absolute", 
  "snoozeBG": 129, 
  "recieved": true, 
  "predBGs": {
    "COB": [
      135, 
      134, 
      134, 
      133, 
      132, 
      130, 
      129, 
      127, 
      125, 
      124, 
      122, 
      121, 
      120, 
      119, 
      118, 
      117, 
      117, 
      117, 
      117, 
      117, 
      117, 
      116
    ], 
    "aCOB": [
      135, 
      138, 
      138, 
      136, 
      132, 
      130, 
      127, 
      125, 
      123, 
      121, 
      119, 
      118, 
      117, 
      116, 
      115, 
      115, 
      114, 
      114, 
      114, 
      114, 
      114, 
      114, 
      114, 
      114, 
      113
    ], 
    "IOB": [
      135, 
      135, 
      134, 
      134, 
      133, 
      132, 
      132, 
      131, 
      130, 
      130, 
      129, 
      128, 
      127, 
      126, 
      125, 
      124, 
      124, 
      124, 
      124, 
      124, 
      124, 
      123
    ]
  }, 
  "rate": 0.7, 
  "reason": "COB: 2, Dev: 23, BGI: -4.02, ISF: 96, Target: 119; Eventual BG 129 >= 119, temp 0.525<0.725U/hr", 
  "COB": 2, 
  "eventualBG": 129, 
  "timestamp": "2016-09-02T08:16:59.333338", 
  "duration": 30, 
  "tick": "+0", 
  "IOB": 0.304
}