{
  "requested": {
    "duration": 30, 
    "rate": 1.15, 
    "temp": "absolute"
  }, 
  "bg": 107, 
  "temp": "absolute", 
  "snoozeBG": 110, 
  "timestamp": "2016-08-31T07:35:25.061224", 
  "predBGs": {
    "COB": [
      107, 
      109, 
      110, 
      110, 
      110, 
      110, 
      109, 
      108, 
      107, 
      106, 
      105, 
      104, 
      103, 
      102, 
      102, 
      101, 
      101, 
      101, 
      101, 
      101, 
      101, 
      101, 
      102, 
      102, 
      103, 
      103, 
      104, 
      105, 
      106, 
      107, 
      107, 
      108, 
      108, 
      109
    ], 
    "aCOB": [
      107, 
      114, 
      120, 
      125, 
      128, 
      131, 
      133, 
      134, 
      134, 
      134, 
      133, 
      132, 
      130, 
      128, 
      125, 
      123, 
      120, 
      118, 
      116, 
      114, 
      112, 
      111, 
      109, 
      108, 
      107, 
      107, 
      106
    ], 
    "IOB": [
      107, 
      108, 
      109, 
      109, 
      108, 
      107, 
      104, 
      102, 
      99, 
      96, 
      92, 
      89, 
      86, 
      82, 
      79, 
      77, 
      74, 
      72, 
      70, 
      68, 
      66, 
      65, 
      63, 
      62, 
      62, 
      61, 
      61, 
      60
    ]
  }, 
  "rate": 0.525, 
  "reason": "COB: 9, Dev: 20, BGI: -2.32, ISF: 95, Target: 80; Eventual BG 109 >= 80, temp 0.525<1.15U/hr", 
  "COB": 9, 
  "eventualBG": 109, 
  "recieved": false, 
  "duration": 22, 
  "tick": "+7", 
  "IOB": 0.699
}