{
  "device": "openaps://indy-e1", 
  "pump": {
    "battery": {
      "status": "normal", 
      "voltage": 1.45
    }, 
    "status": {
      "status": "normal", 
      "timestamp": "2016-09-11T15:53:23.000Z", 
      "bolusing": false, 
      "suspended": false
    }, 
    "reservoir": 75.05, 
    "clock": "2016-09-11T08:53:24-07:00"
  }, 
  "uploader": {
    "battery": 100, 
    "batteryVoltage": 4373
  }, 
  "openaps": {
    "suggested": {
      "bg": 91, 
      "temp": "absolute", 
      "snoozeBG": 119, 
      "timestamp": "2016-09-11T15:55:23.000Z", 
      "predBGs": {
        "IOB": [
          91, 
          90, 
          89, 
          89, 
          89, 
          90, 
          90, 
          91, 
          92, 
          94, 
          95, 
          97, 
          99, 
          101, 
          103, 
          105, 
          107, 
          108, 
          110, 
          112, 
          113, 
          114, 
          115, 
          116, 
          117, 
          118, 
          118, 
          119, 
          119, 
          119, 
          120
        ]
      }, 
      "reason": "COB: 0, Dev: -7, BGI: 0.18, ISF: 90, Target: 115; Eventual BG 119 > 115 but Min. Delta -1.06 < Exp. Delta 0, temp 0.55 ~ req 0.55U/hr", 
      "COB": 0, 
      "eventualBG": 119, 
      "tick": -1, 
      "IOB": -0.392
    }, 
    "iob": {
      "netbasalinsulin": -0.5, 
      "timestamp": "2016-09-11T15:53:24.000Z", 
      "activity": -0.0004, 
      "basaliob": -0.392, 
      "hightempinsulin": 0.55, 
      "bolussnooze": 0, 
      "iob": -0.392
    }, 
    "enacted": {
      "bg": 124, 
      "temp": "absolute", 
      "snoozeBG": 83, 
      "recieved": true, 
      "reason": "COB: 0, Dev: -28, BGI: 0.62, ISF: 89, Target: 114; Eventual BG 83 < 114, setting -0.85U/hr", 
      "rate": 0, 
      "COB": 0, 
      "eventualBG": 83, 
      "timestamp": "2016-09-11T14:56:35.000Z", 
      "duration": 30, 
      "tick": -5, 
      "IOB": 0.145
    }
  }, 
  "mmtune": {
    "scanDetails": [
      [
        "916.588", 
        1, 
        -95
      ], 
      [
        "916.612", 
        5, 
        -78
      ], 
      [
        "916.636", 
        5, 
        -78
      ], 
      [
        "916.660", 
        5, 
        -78
      ], 
      [
        "916.684", 
        5, 
        -80
      ], 
      [
        "916.708", 
        5, 
        -87
      ], 
      [
        "916.732", 
        1, 
        -96
      ]
    ], 
    "setFreq": 916.66, 
    "timestamp": "2016-09-11T15:53:02.000Z", 
    "usedDefault": false
  }
}