{
  "device": "openaps://indy-e1", 
  "pump": {
    "battery": {
      "status": "normal", 
      "voltage": 1.57
    }, 
    "status": {
      "status": "normal", 
      "timestamp": "2016-08-09T07:05:13.000Z", 
      "bolusing": false, 
      "suspended": false
    }, 
    "reservoir": 39.175, 
    "clock": "2016-08-09T00:05:00-07:00"
  }, 
  "uploader": {
    "battery": 100, 
    "batteryVoltage": 4376
  }, 
  "openaps": {
    "suggested": {
      "bg": 187, 
      "temp": "absolute", 
      "snoozeBG": 104, 
      "timestamp": "2016-08-09T07:06:53.000Z", 
      "predBGs": {
        "IOB": [
          187, 
          184, 
          181, 
          178, 
          174, 
          169, 
          165, 
          159, 
          154, 
          148, 
          143, 
          136, 
          130, 
          124, 
          119, 
          114, 
          110, 
          106, 
          103, 
          100, 
          98, 
          96, 
          94, 
          92, 
          91, 
          90, 
          89, 
          88, 
          87, 
          86, 
          86, 
          85, 
          85, 
          85, 
          85, 
          85, 
          84
        ]
      }, 
      "reason": "COB: 0, Dev: 40, BGI: -8.73, ISF: 76.9, Target: 80; Eventual BG 104 >= 80, temp 1.75 >~ req 1.3U/hr", 
      "COB": 0, 
      "eventualBG": 104, 
      "tick": -2, 
      "IOB": 1.599
    }, 
    "iob": [
      {
        "netbasalinsulin": 2, 
        "activity": 0.0227, 
        "basaliob": 1.342, 
        "time": "2016-08-09T07:05:00.000Z", 
        "hightempinsulin": 2.35, 
        "bolussnooze": 0, 
        "iob": 1.599
      }, 
      {
        "netbasalinsulin": 2.1, 
        "activity": 0.0226, 
        "basaliob": 1.357, 
        "time": "2016-08-09T07:10:00.000Z", 
        "hightempinsulin": 2.45, 
        "bolussnooze": 0, 
        "iob": 1.586
      }, 
      {
        "netbasalinsulin": 2.15, 
        "activity": 0.0224, 
        "basaliob": 1.271, 
        "time": "2016-08-09T07:15:00.000Z", 
        "hightempinsulin": 2.45, 
        "bolussnooze": 0, 
        "iob": 1.474
      }, 
      {
        "netbasalinsulin": 2.15, 
        "activity": 0.0221, 
        "basaliob": 1.185, 
        "time": "2016-08-09T07:20:00.000Z", 
        "hightempinsulin": 2.45, 
        "bolussnooze": 0, 
        "iob": 1.363
      }, 
      {
        "netbasalinsulin": 2.2, 
        "activity": 0.0216, 
        "basaliob": 1.1, 
        "time": "2016-08-09T07:25:00.000Z", 
        "hightempinsulin": 2.45, 
        "bolussnooze": 0, 
        "iob": 1.255
      }, 
      {
        "netbasalinsulin": 2.25, 
        "activity": 0.0211, 
        "basaliob": 1.016, 
        "time": "2016-08-09T07:30:00.000Z", 
        "hightempinsulin": 2.45, 
        "bolussnooze": 0, 
        "iob": 1.15
      }, 
      {
        "netbasalinsulin": 2.3, 
        "activity": 0.0205, 
        "basaliob": 0.933, 
        "time": "2016-08-09T07:35:00.000Z", 
        "hightempinsulin": 2.45, 
        "bolussnooze": 0, 
        "iob": 1.047
      }, 
      {
        "netbasalinsulin": 2.35, 
        "activity": 0.0198, 
        "basaliob": 0.852, 
        "time": "2016-08-09T07:40:00.000Z", 
        "hightempinsulin": 2.45, 
        "bolussnooze": 0, 
        "iob": 0.948
      }, 
      {
        "netbasalinsulin": 2.35, 
        "activity": 0.019, 
        "basaliob": 0.774, 
        "time": "2016-08-09T07:45:00.000Z", 
        "hightempinsulin": 2.45, 
        "bolussnooze": 0, 
        "iob": 0.853
      }, 
      {
        "netbasalinsulin": 2.4, 
        "activity": 0.0182, 
        "basaliob": 0.699, 
        "time": "2016-08-09T07:50:00.000Z", 
        "hightempinsulin": 2.45, 
        "bolussnooze": 0, 
        "iob": 0.762
      }, 
      {
        "netbasalinsulin": 2.45, 
        "activity": 0.0172, 
        "basaliob": 0.626, 
        "time": "2016-08-09T07:55:00.000Z", 
        "hightempinsulin": 2.45, 
        "bolussnooze": 0, 
        "iob": 0.676
      }, 
      {
        "netbasalinsulin": 2.45, 
        "activity": 0.0162, 
        "basaliob": 0.557, 
        "time": "2016-08-09T08:00:00.000Z", 
        "hightempinsulin": 2.45, 
        "bolussnooze": 0, 
        "iob": 0.595
      }, 
      {
        "netbasalinsulin": 2.4, 
        "activity": 0.0151, 
        "basaliob": 0.492, 
        "time": "2016-08-09T08:05:00.000Z", 
        "hightempinsulin": 2.4, 
        "bolussnooze": 0, 
        "iob": 0.52
      }, 
      {
        "netbasalinsulin": 2.35, 
        "activity": 0.0138, 
        "basaliob": 0.431, 
        "time": "2016-08-09T08:10:00.000Z", 
        "hightempinsulin": 2.35, 
        "bolussnooze": 0, 
        "iob": 0.451
      }, 
      {
        "netbasalinsulin": 2.3, 
        "activity": 0.0126, 
        "basaliob": 0.376, 
        "time": "2016-08-09T08:15:00.000Z", 
        "hightempinsulin": 2.3, 
        "bolussnooze": 0, 
        "iob": 0.388
      }, 
      {
        "netbasalinsulin": 2.2, 
        "activity": 0.0112, 
        "basaliob": 0.325, 
        "time": "2016-08-09T08:20:00.000Z", 
        "hightempinsulin": 2.2, 
        "bolussnooze": 0, 
        "iob": 0.332
      }, 
      {
        "netbasalinsulin": 2.05, 
        "activity": 0.0098, 
        "basaliob": 0.28, 
        "time": "2016-08-09T08:25:00.000Z", 
        "hightempinsulin": 2.05, 
        "bolussnooze": 0, 
        "iob": 0.283
      }, 
      {
        "netbasalinsulin": 1.9, 
        "activity": 0.0085, 
        "basaliob": 0.24, 
        "time": "2016-08-09T08:30:00.000Z", 
        "hightempinsulin": 1.9, 
        "bolussnooze": 0, 
        "iob": 0.24
      }, 
      {
        "netbasalinsulin": 1.7, 
        "activity": 0.0072, 
        "basaliob": 0.205, 
        "time": "2016-08-09T08:35:00.000Z", 
        "hightempinsulin": 1.7, 
        "bolussnooze": 0, 
        "iob": 0.204
      }, 
      {
        "netbasalinsulin": 1.5, 
        "activity": 0.0062, 
        "basaliob": 0.174, 
        "time": "2016-08-09T08:40:00.000Z", 
        "hightempinsulin": 1.5, 
        "bolussnooze": 0, 
        "iob": 0.174
      }, 
      {
        "netbasalinsulin": 1.35, 
        "activity": 0.0054, 
        "basaliob": 0.146, 
        "time": "2016-08-09T08:45:00.000Z", 
        "hightempinsulin": 1.35, 
        "bolussnooze": 0, 
        "iob": 0.146
      }, 
      {
        "netbasalinsulin": 1.15, 
        "activity": 0.0048, 
        "basaliob": 0.123, 
        "time": "2016-08-09T08:50:00.000Z", 
        "hightempinsulin": 1.15, 
        "bolussnooze": 0, 
        "iob": 0.123
      }, 
      {
        "netbasalinsulin": 0.95, 
        "activity": 0.0042, 
        "basaliob": 0.101, 
        "time": "2016-08-09T08:55:00.000Z", 
        "hightempinsulin": 0.95, 
        "bolussnooze": 0, 
        "iob": 0.101
      }, 
      {
        "netbasalinsulin": 0.95, 
        "activity": 0.0037, 
        "basaliob": 0.083, 
        "time": "2016-08-09T09:00:00.000Z", 
        "hightempinsulin": 0.95, 
        "bolussnooze": 0, 
        "iob": 0.083
      }, 
      {
        "netbasalinsulin": 0.85, 
        "activity": 0.0032, 
        "basaliob": 0.067, 
        "time": "2016-08-09T09:05:00.000Z", 
        "hightempinsulin": 0.85, 
        "bolussnooze": 0, 
        "iob": 0.067
      }, 
      {
        "netbasalinsulin": 0.75, 
        "activity": 0.0028, 
        "basaliob": 0.053, 
        "time": "2016-08-09T09:10:00.000Z", 
        "hightempinsulin": 0.75, 
        "bolussnooze": 0, 
        "iob": 0.053
      }, 
      {
        "netbasalinsulin": 0.75, 
        "activity": 0.0024, 
        "basaliob": 0.041, 
        "time": "2016-08-09T09:15:00.000Z", 
        "hightempinsulin": 0.75, 
        "bolussnooze": 0, 
        "iob": 0.041
      }, 
      {
        "netbasalinsulin": 0.7, 
        "activity": 0.002, 
        "basaliob": 0.03, 
        "time": "2016-08-09T09:20:00.000Z", 
        "hightempinsulin": 0.7, 
        "bolussnooze": 0, 
        "iob": 0.03
      }, 
      {
        "netbasalinsulin": 0.6, 
        "activity": 0.0017, 
        "basaliob": 0.022, 
        "time": "2016-08-09T09:25:00.000Z", 
        "hightempinsulin": 0.6, 
        "bolussnooze": 0, 
        "iob": 0.022
      }, 
      {
        "netbasalinsulin": 0.6, 
        "activity": 0.0014, 
        "basaliob": 0.015, 
        "time": "2016-08-09T09:30:00.000Z", 
        "hightempinsulin": 0.6, 
        "bolussnooze": 0, 
        "iob": 0.015
      }, 
      {
        "netbasalinsulin": 0.55, 
        "activity": 0.0011, 
        "basaliob": 0.01, 
        "time": "2016-08-09T09:35:00.000Z", 
        "hightempinsulin": 0.55, 
        "bolussnooze": 0, 
        "iob": 0.01
      }, 
      {
        "netbasalinsulin": 0.5, 
        "activity": 0.0008, 
        "basaliob": 0.006, 
        "time": "2016-08-09T09:40:00.000Z", 
        "hightempinsulin": 0.5, 
        "bolussnooze": 0, 
        "iob": 0.006
      }, 
      {
        "netbasalinsulin": 0.4, 
        "activity": 0.0005, 
        "basaliob": 0.003, 
        "time": "2016-08-09T09:45:00.000Z", 
        "hightempinsulin": 0.4, 
        "bolussnooze": 0, 
        "iob": 0.003
      }, 
      {
        "netbasalinsulin": 0.35, 
        "activity": 0.0003, 
        "basaliob": 0.001, 
        "time": "2016-08-09T09:50:00.000Z", 
        "hightempinsulin": 0.35, 
        "bolussnooze": 0, 
        "iob": 0.001
      }, 
      {
        "netbasalinsulin": 0.25, 
        "activity": 0.0002, 
        "basaliob": 0, 
        "time": "2016-08-09T09:55:00.000Z", 
        "hightempinsulin": 0.25, 
        "bolussnooze": 0, 
        "iob": 0
      }, 
      {
        "netbasalinsulin": 0.15, 
        "activity": 0.0001, 
        "basaliob": 0, 
        "time": "2016-08-09T10:00:00.000Z", 
        "hightempinsulin": 0.15, 
        "bolussnooze": 0, 
        "iob": 0
      }
    ], 
    "enacted": {
      "bg": 190, 
      "temp": "absolute", 
      "snoozeBG": 116, 
      "recieved": true, 
      "predBGs": {
        "COB": [
          190, 
          191, 
          190, 
          189, 
          187, 
          184, 
          181, 
          177, 
          172, 
          168, 
          163, 
          158, 
          154, 
          149, 
          145, 
          140, 
          136, 
          132, 
          128, 
          124, 
          121, 
          118, 
          116, 
          114, 
          112, 
          111, 
          110, 
          109, 
          109, 
          108, 
          108, 
          108, 
          108, 
          108, 
          107
        ], 
        "aCOB": [
          190, 
          195, 
          199, 
          202, 
          204, 
          204, 
          203, 
          201, 
          198, 
          195, 
          191, 
          187, 
          182, 
          177, 
          172, 
          166, 
          159, 
          153, 
          147, 
          141, 
          136, 
          131, 
          126, 
          122, 
          119, 
          116, 
          114, 
          112, 
          111, 
          109, 
          108, 
          107, 
          106, 
          106, 
          105, 
          105, 
          104
        ], 
        "IOB": [
          190, 
          190, 
          189, 
          187, 
          184, 
          180, 
          175, 
          169, 
          163, 
          156, 
          148, 
          141, 
          133, 
          125, 
          118, 
          111, 
          104, 
          97, 
          91, 
          85, 
          80, 
          75, 
          71, 
          67, 
          63, 
          61, 
          58, 
          56, 
          55, 
          54, 
          52, 
          51, 
          51, 
          50, 
          49
        ]
      }, 
      "reason": "COB: 18, Dev: 28, BGI: -4.04, ISF: 76.9, Target: 113; Eventual BG 107 < 113, but Delta +2 > Exp. Delta -2.7; setting current basal of 0.875 as temp", 
      "rate": 0.875, 
      "COB": 18, 
      "eventualBG": 107, 
      "timestamp": "2016-08-09T06:25:21.000Z", 
      "duration": 30, 
      "tick": "+2", 
      "IOB": 1.679
    }
  }, 
  "mmtune": {
    "scanDetails": [
      [
        "916.564", 
        5, 
        -88
      ], 
      [
        "916.588", 
        5, 
        -82
      ], 
      [
        "916.612", 
        5, 
        -81
      ], 
      [
        "916.636", 
        5, 
        -81
      ], 
      [
        "916.660", 
        5, 
        -81
      ], 
      [
        "916.684", 
        5, 
        -82
      ], 
      [
        "916.708", 
        5, 
        -87
      ]
    ], 
    "setFreq": 916.66, 
    "timestamp": "2016-08-09T07:04:50.000Z", 
    "usedDefault": false
  }
}