{
  "device": "openaps://indy-e1", 
  "pump": {
    "battery": {
      "status": "normal", 
      "voltage": 1.55
    }, 
    "status": {
      "status": "normal", 
      "timestamp": "2016-09-03T13:37:20.000Z", 
      "bolusing": false, 
      "suspended": false
    }, 
    "reservoir": 144.925, 
    "clock": "2016-09-03T06:37:17-07:00"
  }, 
  "uploader": {
    "battery": 100, 
    "batteryVoltage": 4367
  }, 
  "openaps": {
    "suggested": {
      "bg": 81, 
      "temp": "absolute", 
      "snoozeBG": 122, 
      "timestamp": "2016-09-03T13:39:11.000Z", 
      "predBGs": {
        "IOB": [
          81, 
          83, 
          84, 
          86, 
          88, 
          90, 
          93, 
          95, 
          98, 
          100, 
          103, 
          106, 
          108, 
          111, 
          113, 
          115, 
          118, 
          119, 
          121, 
          123, 
          124, 
          125, 
          126, 
          127, 
          128, 
          128, 
          129, 
          129, 
          130
        ]
      }, 
      "reason": "COB: 0, Dev: -7, BGI: 2.55, ISF: 100, Target: 121; BG 81<86, delta 5>0, temp 0.45 ~ req 0.45U/hr", 
      "COB": 0, 
      "eventualBG": 122, 
      "tick": "+5", 
      "IOB": -0.528
    }, 
    "iob": {
      "netbasalinsulin": -1, 
      "timestamp": "2016-09-03T13:37:17.000Z", 
      "activity": -0.0051, 
      "basaliob": -0.528, 
      "hightempinsulin": 0, 
      "bolussnooze": 0, 
      "iob": -0.528
    }, 
    "enacted": {
      "bg": 76, 
      "temp": "absolute", 
      "snoozeBG": 112, 
      "recieved": true, 
      "reason": "COB: 0, Dev: -14, BGI: 2.45, ISF: 100, Target: 121; BG 76<86, delta 4>0; setting current basal of 0.45 as temp", 
      "rate": 0.45, 
      "COB": 0, 
      "eventualBG": 112, 
      "timestamp": "2016-09-03T13:34:30.000Z", 
      "duration": 30, 
      "tick": "+4", 
      "IOB": -0.553
    }
  }, 
  "mmtune": {
    "scanDetails": [
      [
        "916.564", 
        5, 
        -78
      ], 
      [
        "916.588", 
        5, 
        -71
      ], 
      [
        "916.612", 
        5, 
        -67
      ], 
      [
        "916.636", 
        5, 
        -67
      ], 
      [
        "916.660", 
        5, 
        -67
      ], 
      [
        "916.684", 
        5, 
        -71
      ], 
      [
        "916.708", 
        5, 
        -77
      ]
    ], 
    "setFreq": 916.66, 
    "timestamp": "2016-09-03T13:36:58.000Z", 
    "usedDefault": false
  }
}