{
  "device": "openaps://indy-e1", 
  "pump": {
    "battery": {
      "status": "normal", 
      "voltage": 1.57
    }, 
    "status": {
      "status": "normal", 
      "timestamp": "2016-08-03T04:31:53.000Z", 
      "bolusing": false, 
      "suspended": false
    }, 
    "reservoir": 146.575, 
    "clock": "2016-08-02T21:31:21-07:00"
  }, 
  "uploader": {
    "battery": 100, 
    "batteryVoltage": 4376
  }, 
  "openaps": {
    "suggested": {
      "bg": 125, 
      "temp": "absolute", 
      "snoozeBG": 70, 
      "timestamp": "2016-08-03T04:33:25.000Z", 
      "predBGs": {
        "aCOB": [
          125, 
          125, 
          124, 
          121, 
          117, 
          112, 
          108, 
          104, 
          100, 
          97, 
          95, 
          94, 
          93, 
          92, 
          92, 
          92, 
          93, 
          93, 
          94, 
          95, 
          96, 
          97, 
          98, 
          99, 
          100, 
          101, 
          102, 
          103, 
          104, 
          105, 
          106, 
          106, 
          107, 
          107, 
          108
        ], 
        "IOB": [
          125, 
          117, 
          110, 
          103, 
          97, 
          92, 
          88, 
          84, 
          80, 
          77, 
          75, 
          74, 
          73, 
          72, 
          72, 
          72, 
          73, 
          73, 
          74, 
          75, 
          76, 
          77, 
          78, 
          79, 
          80, 
          81, 
          82, 
          83, 
          84, 
          85, 
          86, 
          86, 
          87, 
          87, 
          88
        ]
      }, 
      "reason": "COB: 5, Dev: -26, BGI: -3.84, ISF: 80, Target: 115; Eventual BG 70 < 115, setting -1.5U/hr, but 24m left and 0 ~ req 0U/hr: no action required", 
      "COB": 5, 
      "eventualBG": 70, 
      "tick": -4, 
      "IOB": 0.358
    }, 
    "iob": [
      {
        "netbasalinsulin": 0.05, 
        "activity": 0.0096, 
        "basaliob": 0.325, 
        "time": "2016-08-03T04:31:21.000Z", 
        "hightempinsulin": 0.95, 
        "bolussnooze": 0, 
        "iob": 0.358
      }, 
      {
        "netbasalinsulin": 0.05, 
        "activity": 0.0091, 
        "basaliob": 0.244, 
        "time": "2016-08-03T04:36:21.000Z", 
        "hightempinsulin": 0.95, 
        "bolussnooze": 0, 
        "iob": 0.263
      }, 
      {
        "netbasalinsulin": 0.05, 
        "activity": 0.0084, 
        "basaliob": 0.163, 
        "time": "2016-08-03T04:41:21.000Z", 
        "hightempinsulin": 0.95, 
        "bolussnooze": 0, 
        "iob": 0.171
      }, 
      {
        "netbasalinsulin": 0.05, 
        "activity": 0.0075, 
        "basaliob": 0.082, 
        "time": "2016-08-03T04:46:21.000Z", 
        "hightempinsulin": 0.95, 
        "bolussnooze": 0, 
        "iob": 0.083
      }, 
      {
        "netbasalinsulin": 0.1, 
        "activity": 0.0064, 
        "basaliob": 0.001, 
        "time": "2016-08-03T04:51:21.000Z", 
        "hightempinsulin": 0.95, 
        "bolussnooze": 0, 
        "iob": 0.001
      }, 
      {
        "netbasalinsulin": 0.1, 
        "activity": 0.0058, 
        "basaliob": -0.078, 
        "time": "2016-08-03T04:56:21.000Z", 
        "hightempinsulin": 0.95, 
        "bolussnooze": 0, 
        "iob": -0.078
      }, 
      {
        "netbasalinsulin": 0.1, 
        "activity": 0.0054, 
        "basaliob": -0.105, 
        "time": "2016-08-03T05:01:21.000Z", 
        "hightempinsulin": 0.95, 
        "bolussnooze": 0, 
        "iob": -0.105
      }, 
      {
        "netbasalinsulin": 0.15, 
        "activity": 0.0048, 
        "basaliob": -0.129, 
        "time": "2016-08-03T05:06:21.000Z", 
        "hightempinsulin": 0.95, 
        "bolussnooze": 0, 
        "iob": -0.129
      }, 
      {
        "netbasalinsulin": 0.2, 
        "activity": 0.0043, 
        "basaliob": -0.15, 
        "time": "2016-08-03T05:11:21.000Z", 
        "hightempinsulin": 0.95, 
        "bolussnooze": 0, 
        "iob": -0.15
      }, 
      {
        "netbasalinsulin": 0.3, 
        "activity": 0.0036, 
        "basaliob": -0.168, 
        "time": "2016-08-03T05:16:21.000Z", 
        "hightempinsulin": 0.95, 
        "bolussnooze": 0, 
        "iob": -0.168
      }, 
      {
        "netbasalinsulin": 0.35, 
        "activity": 0.0028, 
        "basaliob": -0.182, 
        "time": "2016-08-03T05:21:21.000Z", 
        "hightempinsulin": 0.95, 
        "bolussnooze": 0, 
        "iob": -0.182
      }, 
      {
        "netbasalinsulin": 0.4, 
        "activity": 0.002, 
        "basaliob": -0.192, 
        "time": "2016-08-03T05:26:21.000Z", 
        "hightempinsulin": 0.95, 
        "bolussnooze": 0, 
        "iob": -0.192
      }, 
      {
        "netbasalinsulin": 0.45, 
        "activity": 0.0012, 
        "basaliob": -0.198, 
        "time": "2016-08-03T05:31:21.000Z", 
        "hightempinsulin": 0.95, 
        "bolussnooze": 0, 
        "iob": -0.198
      }, 
      {
        "netbasalinsulin": 0.45, 
        "activity": 0.0004, 
        "basaliob": -0.2, 
        "time": "2016-08-03T05:36:21.000Z", 
        "hightempinsulin": 0.95, 
        "bolussnooze": 0, 
        "iob": -0.2
      }, 
      {
        "netbasalinsulin": 0.4, 
        "activity": -0.0003, 
        "basaliob": -0.198, 
        "time": "2016-08-03T05:41:21.000Z", 
        "hightempinsulin": 0.9, 
        "bolussnooze": 0, 
        "iob": -0.198
      }, 
      {
        "netbasalinsulin": 0.4, 
        "activity": -0.0009, 
        "basaliob": -0.194, 
        "time": "2016-08-03T05:46:21.000Z", 
        "hightempinsulin": 0.9, 
        "bolussnooze": 0, 
        "iob": -0.194
      }, 
      {
        "netbasalinsulin": 0.4, 
        "activity": -0.0014, 
        "basaliob": -0.187, 
        "time": "2016-08-03T05:51:21.000Z", 
        "hightempinsulin": 0.9, 
        "bolussnooze": 0, 
        "iob": -0.187
      }, 
      {
        "netbasalinsulin": 0.35, 
        "activity": -0.0018, 
        "basaliob": -0.178, 
        "time": "2016-08-03T05:56:21.000Z", 
        "hightempinsulin": 0.85, 
        "bolussnooze": 0, 
        "iob": -0.178
      }, 
      {
        "netbasalinsulin": 0.3, 
        "activity": -0.0021, 
        "basaliob": -0.168, 
        "time": "2016-08-03T06:01:21.000Z", 
        "hightempinsulin": 0.8, 
        "bolussnooze": 0, 
        "iob": -0.168
      }, 
      {
        "netbasalinsulin": 0.25, 
        "activity": -0.0024, 
        "basaliob": -0.156, 
        "time": "2016-08-03T06:06:21.000Z", 
        "hightempinsulin": 0.75, 
        "bolussnooze": 0, 
        "iob": -0.156
      }, 
      {
        "netbasalinsulin": 0.25, 
        "activity": -0.0025, 
        "basaliob": -0.143, 
        "time": "2016-08-03T06:11:21.000Z", 
        "hightempinsulin": 0.75, 
        "bolussnooze": 0, 
        "iob": -0.143
      }, 
      {
        "netbasalinsulin": 0.15, 
        "activity": -0.0026, 
        "basaliob": -0.13, 
        "time": "2016-08-03T06:16:21.000Z", 
        "hightempinsulin": 0.65, 
        "bolussnooze": 0, 
        "iob": -0.13
      }, 
      {
        "netbasalinsulin": 0.05, 
        "activity": -0.0027, 
        "basaliob": -0.117, 
        "time": "2016-08-03T06:21:21.000Z", 
        "hightempinsulin": 0.55, 
        "bolussnooze": 0, 
        "iob": -0.117
      }, 
      {
        "netbasalinsulin": 0, 
        "activity": -0.0027, 
        "basaliob": -0.104, 
        "time": "2016-08-03T06:26:21.000Z", 
        "hightempinsulin": 0.5, 
        "bolussnooze": 0, 
        "iob": -0.104
      }, 
      {
        "netbasalinsulin": -0.1, 
        "activity": -0.0026, 
        "basaliob": -0.09, 
        "time": "2016-08-03T06:31:21.000Z", 
        "hightempinsulin": 0.4, 
        "bolussnooze": 0, 
        "iob": -0.09
      }, 
      {
        "netbasalinsulin": -0.2, 
        "activity": -0.0026, 
        "basaliob": -0.078, 
        "time": "2016-08-03T06:36:21.000Z", 
        "hightempinsulin": 0.3, 
        "bolussnooze": 0, 
        "iob": -0.078
      }, 
      {
        "netbasalinsulin": -0.3, 
        "activity": -0.0024, 
        "basaliob": -0.065, 
        "time": "2016-08-03T06:41:21.000Z", 
        "hightempinsulin": 0.2, 
        "bolussnooze": 0, 
        "iob": -0.065
      }, 
      {
        "netbasalinsulin": -0.3, 
        "activity": -0.0023, 
        "basaliob": -0.054, 
        "time": "2016-08-03T06:46:21.000Z", 
        "hightempinsulin": 0.2, 
        "bolussnooze": 0, 
        "iob": -0.054
      }, 
      {
        "netbasalinsulin": -0.35, 
        "activity": -0.0021, 
        "basaliob": -0.044, 
        "time": "2016-08-03T06:51:21.000Z", 
        "hightempinsulin": 0.15, 
        "bolussnooze": 0, 
        "iob": -0.044
      }, 
      {
        "netbasalinsulin": -0.4, 
        "activity": -0.0019, 
        "basaliob": -0.034, 
        "time": "2016-08-03T06:56:21.000Z", 
        "hightempinsulin": 0.1, 
        "bolussnooze": 0, 
        "iob": -0.034
      }, 
      {
        "netbasalinsulin": -0.45, 
        "activity": -0.0017, 
        "basaliob": -0.026, 
        "time": "2016-08-03T07:01:21.000Z", 
        "hightempinsulin": 0.05, 
        "bolussnooze": 0, 
        "iob": -0.026
      }, 
      {
        "netbasalinsulin": -0.5, 
        "activity": -0.0014, 
        "basaliob": -0.019, 
        "time": "2016-08-03T07:06:21.000Z", 
        "hightempinsulin": 0, 
        "bolussnooze": 0, 
        "iob": -0.019
      }, 
      {
        "netbasalinsulin": -0.5, 
        "activity": -0.0011, 
        "basaliob": -0.013, 
        "time": "2016-08-03T07:11:21.000Z", 
        "hightempinsulin": 0, 
        "bolussnooze": 0, 
        "iob": -0.013
      }, 
      {
        "netbasalinsulin": -0.45, 
        "activity": -0.0009, 
        "basaliob": -0.009, 
        "time": "2016-08-03T07:16:21.000Z", 
        "hightempinsulin": 0, 
        "bolussnooze": 0, 
        "iob": -0.009
      }, 
      {
        "netbasalinsulin": -0.4, 
        "activity": -0.0007, 
        "basaliob": -0.006, 
        "time": "2016-08-03T07:21:21.000Z", 
        "hightempinsulin": 0, 
        "bolussnooze": 0, 
        "iob": -0.006
      }, 
      {
        "netbasalinsulin": -0.35, 
        "activity": -0.0005, 
        "basaliob": -0.003, 
        "time": "2016-08-03T07:26:21.000Z", 
        "hightempinsulin": 0, 
        "bolussnooze": 0, 
        "iob": -0.003
      }
    ]
  }, 
  "mmtune": {
    "scanDetails": [
      [
        "916.636", 
        2, 
        -89
      ], 
      [
        "916.660", 
        5, 
        -73
      ], 
      [
        "916.684", 
        5, 
        -75
      ], 
      [
        "916.708", 
        5, 
        -83
      ]
    ], 
    "setFreq": 916.66, 
    "timestamp": "2016-08-03T04:31:13.000Z", 
    "usedDefault": false
  }
}