{
  "device": "openaps://indy-e1", 
  "pump": {
    "battery": {
      "status": "normal", 
      "voltage": 1.41
    }, 
    "status": {
      "status": "normal", 
      "timestamp": "2016-09-01T02:15:53.000Z", 
      "bolusing": false, 
      "suspended": false
    }, 
    "reservoir": 124.825, 
    "clock": "2016-08-31T19:15:50-07:00"
  }, 
  "uploader": {
    "battery": 100, 
    "batteryVoltage": 4364
  }, 
  "openaps": {
    "suggested": {
      "bg": 106, 
      "temp": "absolute", 
      "snoozeBG": 99, 
      "timestamp": "2016-09-01T02:17:20.000Z", 
      "rate": 0.575, 
      "reason": "COB: 24, Dev: 21, BGI: -5.45, ISF: 100, Target: 121; 189-99 in range: no temp required; setting current basal of 0.575 as temp", 
      "COB": 24, 
      "eventualBG": 189, 
      "duration": 30, 
      "tick": "+1", 
      "IOB": 0.375
    }, 
    "iob": {
      "netbasalinsulin": -0.25, 
      "timestamp": "2016-09-01T02:15:50.000Z", 
      "activity": 0.0109, 
      "basaliob": -0.012, 
      "hightempinsulin": 0.45, 
      "bolussnooze": 0, 
      "iob": 0.375
    }, 
    "enacted": {
      "bg": 106, 
      "temp": "absolute", 
      "snoozeBG": 99, 
      "recieved": true, 
      "predBGs": {
        "COB": [
          106, 
          104, 
          102, 
          101, 
          99, 
          98, 
          98, 
          98, 
          98, 
          99, 
          100, 
          101, 
          103, 
          105, 
          108, 
          111, 
          114, 
          118, 
          122, 
          126, 
          130, 
          134, 
          138, 
          142, 
          145, 
          149, 
          152, 
          156, 
          159, 
          162, 
          164, 
          167, 
          170, 
          172, 
          174, 
          176, 
          178, 
          180, 
          182, 
          184, 
          185, 
          187, 
          189
        ], 
        "aCOB": [
          106, 
          110, 
          114, 
          118, 
          122, 
          126, 
          130, 
          134, 
          138, 
          142, 
          146, 
          151, 
          155, 
          160, 
          164, 
          169, 
          174, 
          178, 
          183, 
          187, 
          191, 
          195, 
          198, 
          200, 
          203, 
          204, 
          206, 
          207, 
          208, 
          209, 
          209, 
          210, 
          210, 
          211
        ], 
        "IOB": [
          106, 
          104, 
          101, 
          99, 
          97, 
          95, 
          93, 
          91, 
          89, 
          87, 
          86, 
          85, 
          84, 
          83, 
          83, 
          83, 
          84, 
          85, 
          86, 
          87, 
          89, 
          90, 
          92, 
          93, 
          94, 
          96, 
          97, 
          98, 
          99, 
          99, 
          100, 
          101, 
          101, 
          102
        ]
      }, 
      "reason": "COB: 24, Dev: 21, BGI: -5.45, ISF: 100, Target: 121; 189-99 in range: no temp required; setting current basal of 0.575 as temp", 
      "rate": 0.55, 
      "COB": 24, 
      "eventualBG": 189, 
      "timestamp": "2016-09-01T02:17:33.000Z", 
      "duration": 30, 
      "tick": "+1", 
      "IOB": 0.375
    }
  }, 
  "mmtune": {
    "scanDetails": [
      [
        "916.564", 
        5, 
        -78
      ], 
      [
        "916.588", 
        5, 
        -76
      ], 
      [
        "916.612", 
        5, 
        -77
      ], 
      [
        "916.636", 
        5, 
        -75
      ], 
      [
        "916.660", 
        5, 
        -75
      ], 
      [
        "916.684", 
        5, 
        -76
      ], 
      [
        "916.708", 
        5, 
        -88
      ]
    ], 
    "setFreq": 916.66, 
    "timestamp": "2016-09-01T02:15:33.000Z", 
    "usedDefault": false
  }
}