{
  "device": "openaps://indy-e1", 
  "pump": {
    "battery": {
      "status": "normal", 
      "voltage": 1.4
    }, 
    "status": {
      "status": "normal", 
      "timestamp": "2016-08-20T22:24:07.000Z", 
      "bolusing": false, 
      "suspended": false
    }, 
    "reservoir": 100.75, 
    "clock": "2016-08-20T15:24:00-07:00"
  }, 
  "uploader": {
    "battery": 67, 
    "batteryVoltage": 3847
  }, 
  "openaps": {
    "suggested": {
      "timestamp": "2016-08-20T22:25:34.000Z", 
      "reason": "CGM is calibrating or in ??? state; setting current basal of 0.525 as temp, but 26m left and 0.525 ~ req 0.525U/hr: no action required"
    }, 
    "iob": {
      "netbasalinsulin": -0.6, 
      "timestamp": "2016-08-20T22:24:00.000Z", 
      "activity": 0.0008, 
      "basaliob": -0.144, 
      "hightempinsulin": 0.3, 
      "bolussnooze": 0.143, 
      "iob": 0.339
    }, 
    "enacted": {
      "bg": 108, 
      "temp": "absolute", 
      "snoozeBG": 121, 
      "recieved": true, 
      "reason": "COB: 25, Dev: -11, BGI: 0.11, ISF: 112.5, Target: 129; Eventual BG 181 > 129 but Delta -8 < Exp. Delta 4.3; setting current basal of 0.525 as temp", 
      "rate": 0.525, 
      "COB": 25, 
      "eventualBG": 181, 
      "timestamp": "2016-08-20T22:20:19.000Z", 
      "duration": 30, 
      "tick": -8, 
      "IOB": 0.393
    }
  }, 
  "mmtune": {
    "scanDetails": [
      [
        "916.564", 
        5, 
        -62
      ], 
      [
        "916.588", 
        5, 
        -58
      ], 
      [
        "916.612", 
        5, 
        -57
      ], 
      [
        "916.636", 
        5, 
        -59
      ], 
      [
        "916.660", 
        5, 
        -54
      ], 
      [
        "916.684", 
        5, 
        -56
      ], 
      [
        "916.708", 
        1, 
        -93
      ]
    ], 
    "setFreq": 916.66, 
    "timestamp": "2016-08-20T22:23:54.000Z", 
    "usedDefault": false
  }
}