{
  "device": "openaps://indy-e1", 
  "pump": {
    "battery": {
      "status": "normal", 
      "voltage": 1.57
    }, 
    "status": {
      "status": "normal", 
      "timestamp": "2016-08-09T05:52:45.000Z", 
      "bolusing": false, 
      "suspended": false
    }, 
    "reservoir": 40.975, 
    "clock": "2016-08-08T22:52:33-07:00"
  }, 
  "uploader": {
    "battery": 100, 
    "batteryVoltage": 4365
  }, 
  "openaps": {
    "suggested": {
      "bg": 173, 
      "temp": "absolute", 
      "snoozeBG": 153, 
      "timestamp": "2016-08-09T05:54:31.000Z", 
      "predBGs": {
        "COB": [
          173, 
          179, 
          184, 
          188, 
          192, 
          195, 
          197, 
          198, 
          198, 
          198, 
          197, 
          195, 
          192, 
          189, 
          186, 
          183, 
          179, 
          176, 
          173, 
          170, 
          168, 
          165, 
          163, 
          161, 
          159, 
          158, 
          156, 
          155, 
          154, 
          153
        ], 
        "aCOB": [
          173, 
          182, 
          190, 
          198, 
          204, 
          209, 
          213, 
          216, 
          218, 
          219, 
          219, 
          217, 
          215, 
          213, 
          209, 
          206, 
          202, 
          198, 
          194, 
          190, 
          186, 
          182, 
          177, 
          173, 
          169, 
          166, 
          162, 
          160, 
          157, 
          155, 
          154, 
          153, 
          152, 
          151
        ], 
        "IOB": [
          173, 
          178, 
          183, 
          186, 
          188, 
          190, 
          189, 
          188, 
          186, 
          182, 
          177, 
          171, 
          164, 
          157, 
          150, 
          143, 
          136, 
          130, 
          124, 
          118, 
          112, 
          107, 
          102, 
          98, 
          94, 
          90, 
          87, 
          85, 
          82, 
          80, 
          79, 
          78, 
          77, 
          76
        ]
      }, 
      "reason": "COB: 24, Dev: 39, BGI: -0.42, ISF: 76.9, Target: 80; Eventual BG 153 >= 80, temp 2.95 >~ req 2.75U/hr", 
      "COB": 24, 
      "eventualBG": 153, 
      "tick": "+6", 
      "IOB": 1.617
    }, 
    "iob": [
      {
        "netbasalinsulin": 1.2, 
        "activity": 0.0011, 
        "basaliob": 1.031, 
        "time": "2016-08-09T05:52:33.000Z", 
        "hightempinsulin": 1.85, 
        "bolussnooze": 0.553, 
        "iob": 1.617
      }, 
      {
        "netbasalinsulin": 1.3, 
        "activity": 0.0024, 
        "basaliob": 1.128, 
        "time": "2016-08-09T05:57:33.000Z", 
        "hightempinsulin": 1.95, 
        "bolussnooze": 0.519, 
        "iob": 1.705
      }, 
      {
        "netbasalinsulin": 1.3, 
        "activity": 0.0038, 
        "basaliob": 1.12, 
        "time": "2016-08-09T06:02:33.000Z", 
        "hightempinsulin": 1.95, 
        "bolussnooze": 0.477, 
        "iob": 1.686
      }, 
      {
        "netbasalinsulin": 1.3, 
        "activity": 0.0053, 
        "basaliob": 1.106, 
        "time": "2016-08-09T06:07:33.000Z", 
        "hightempinsulin": 1.95, 
        "bolussnooze": 0.425, 
        "iob": 1.659
      }, 
      {
        "netbasalinsulin": 1.25, 
        "activity": 0.0069, 
        "basaliob": 1.087, 
        "time": "2016-08-09T06:12:33.000Z", 
        "hightempinsulin": 1.9, 
        "bolussnooze": 0.365, 
        "iob": 1.625
      }, 
      {
        "netbasalinsulin": 1.1, 
        "activity": 0.0086, 
        "basaliob": 1.062, 
        "time": "2016-08-09T06:17:33.000Z", 
        "hightempinsulin": 1.75, 
        "bolussnooze": 0.3, 
        "iob": 1.582
      }, 
      {
        "netbasalinsulin": 0.95, 
        "activity": 0.0103, 
        "basaliob": 1.031, 
        "time": "2016-08-09T06:22:33.000Z", 
        "hightempinsulin": 1.6, 
        "bolussnooze": 0.242, 
        "iob": 1.531
      }, 
      {
        "netbasalinsulin": 0.8, 
        "activity": 0.012, 
        "basaliob": 0.993, 
        "time": "2016-08-09T06:27:33.000Z", 
        "hightempinsulin": 1.45, 
        "bolussnooze": 0.189, 
        "iob": 1.471
      }, 
      {
        "netbasalinsulin": 0.8, 
        "activity": 0.0137, 
        "basaliob": 0.95, 
        "time": "2016-08-09T06:32:33.000Z", 
        "hightempinsulin": 1.45, 
        "bolussnooze": 0.143, 
        "iob": 1.402
      }, 
      {
        "netbasalinsulin": 0.8, 
        "activity": 0.0153, 
        "basaliob": 0.9, 
        "time": "2016-08-09T06:37:33.000Z", 
        "hightempinsulin": 1.45, 
        "bolussnooze": 0.104, 
        "iob": 1.326
      }, 
      {
        "netbasalinsulin": 0.85, 
        "activity": 0.0167, 
        "basaliob": 0.845, 
        "time": "2016-08-09T06:42:33.000Z", 
        "hightempinsulin": 1.45, 
        "bolussnooze": 0.071, 
        "iob": 1.242
      }, 
      {
        "netbasalinsulin": 0.9, 
        "activity": 0.0178, 
        "basaliob": 0.787, 
        "time": "2016-08-09T06:47:33.000Z", 
        "hightempinsulin": 1.45, 
        "bolussnooze": 0.044, 
        "iob": 1.153
      }, 
      {
        "netbasalinsulin": 0.95, 
        "activity": 0.0187, 
        "basaliob": 0.727, 
        "time": "2016-08-09T06:52:33.000Z", 
        "hightempinsulin": 1.45, 
        "bolussnooze": 0.023, 
        "iob": 1.059
      }, 
      {
        "netbasalinsulin": 0.95, 
        "activity": 0.0186, 
        "basaliob": 0.665, 
        "time": "2016-08-09T06:57:33.000Z", 
        "hightempinsulin": 1.45, 
        "bolussnooze": 0.009, 
        "iob": 0.966
      }, 
      {
        "netbasalinsulin": 1, 
        "activity": 0.0183, 
        "basaliob": 0.604, 
        "time": "2016-08-09T07:02:33.000Z", 
        "hightempinsulin": 1.45, 
        "bolussnooze": 0.002, 
        "iob": 0.874
      }, 
      {
        "netbasalinsulin": 1, 
        "activity": 0.0177, 
        "basaliob": 0.543, 
        "time": "2016-08-09T07:07:33.000Z", 
        "hightempinsulin": 1.45, 
        "bolussnooze": 0, 
        "iob": 0.786
      }, 
      {
        "netbasalinsulin": 1, 
        "activity": 0.0169, 
        "basaliob": 0.486, 
        "time": "2016-08-09T07:12:33.000Z", 
        "hightempinsulin": 1.45, 
        "bolussnooze": 0, 
        "iob": 0.701
      }, 
      {
        "netbasalinsulin": 1.05, 
        "activity": 0.016, 
        "basaliob": 0.431, 
        "time": "2016-08-09T07:17:33.000Z", 
        "hightempinsulin": 1.45, 
        "bolussnooze": 0, 
        "iob": 0.621
      }, 
      {
        "netbasalinsulin": 1.05, 
        "activity": 0.0152, 
        "basaliob": 0.379, 
        "time": "2016-08-09T07:22:33.000Z", 
        "hightempinsulin": 1.45, 
        "bolussnooze": 0, 
        "iob": 0.545
      }, 
      {
        "netbasalinsulin": 1.15, 
        "activity": 0.0143, 
        "basaliob": 0.33, 
        "time": "2016-08-09T07:27:33.000Z", 
        "hightempinsulin": 1.45, 
        "bolussnooze": 0, 
        "iob": 0.474
      }, 
      {
        "netbasalinsulin": 1.2, 
        "activity": 0.0133, 
        "basaliob": 0.284, 
        "time": "2016-08-09T07:32:33.000Z", 
        "hightempinsulin": 1.45, 
        "bolussnooze": 0, 
        "iob": 0.407
      }, 
      {
        "netbasalinsulin": 1.3, 
        "activity": 0.0124, 
        "basaliob": 0.241, 
        "time": "2016-08-09T07:37:33.000Z", 
        "hightempinsulin": 1.45, 
        "bolussnooze": 0, 
        "iob": 0.345
      }, 
      {
        "netbasalinsulin": 1.3, 
        "activity": 0.0113, 
        "basaliob": 0.202, 
        "time": "2016-08-09T07:42:33.000Z", 
        "hightempinsulin": 1.45, 
        "bolussnooze": 0, 
        "iob": 0.289
      }, 
      {
        "netbasalinsulin": 1.3, 
        "activity": 0.0103, 
        "basaliob": 0.166, 
        "time": "2016-08-09T07:47:33.000Z", 
        "hightempinsulin": 1.45, 
        "bolussnooze": 0, 
        "iob": 0.237
      }, 
      {
        "netbasalinsulin": 1.4, 
        "activity": 0.0093, 
        "basaliob": 0.134, 
        "time": "2016-08-09T07:52:33.000Z", 
        "hightempinsulin": 1.45, 
        "bolussnooze": 0, 
        "iob": 0.19
      }, 
      {
        "netbasalinsulin": 1.45, 
        "activity": 0.0082, 
        "basaliob": 0.105, 
        "time": "2016-08-09T07:57:33.000Z", 
        "hightempinsulin": 1.45, 
        "bolussnooze": 0, 
        "iob": 0.149
      }, 
      {
        "netbasalinsulin": 1.45, 
        "activity": 0.0071, 
        "basaliob": 0.08, 
        "time": "2016-08-09T08:02:33.000Z", 
        "hightempinsulin": 1.45, 
        "bolussnooze": 0, 
        "iob": 0.114
      }, 
      {
        "netbasalinsulin": 1.4, 
        "activity": 0.0061, 
        "basaliob": 0.06, 
        "time": "2016-08-09T08:07:33.000Z", 
        "hightempinsulin": 1.4, 
        "bolussnooze": 0, 
        "iob": 0.083
      }, 
      {
        "netbasalinsulin": 1.35, 
        "activity": 0.005, 
        "basaliob": 0.042, 
        "time": "2016-08-09T08:12:33.000Z", 
        "hightempinsulin": 1.35, 
        "bolussnooze": 0, 
        "iob": 0.058
      }, 
      {
        "netbasalinsulin": 1.3, 
        "activity": 0.004, 
        "basaliob": 0.029, 
        "time": "2016-08-09T08:17:33.000Z", 
        "hightempinsulin": 1.3, 
        "bolussnooze": 0, 
        "iob": 0.038
      }, 
      {
        "netbasalinsulin": 1.15, 
        "activity": 0.003, 
        "basaliob": 0.018, 
        "time": "2016-08-09T08:22:33.000Z", 
        "hightempinsulin": 1.15, 
        "bolussnooze": 0, 
        "iob": 0.023
      }, 
      {
        "netbasalinsulin": 1.05, 
        "activity": 0.0021, 
        "basaliob": 0.01, 
        "time": "2016-08-09T08:27:33.000Z", 
        "hightempinsulin": 1.05, 
        "bolussnooze": 0, 
        "iob": 0.012
      }, 
      {
        "netbasalinsulin": 0.85, 
        "activity": 0.0013, 
        "basaliob": 0.005, 
        "time": "2016-08-09T08:32:33.000Z", 
        "hightempinsulin": 0.85, 
        "bolussnooze": 0, 
        "iob": 0.005
      }, 
      {
        "netbasalinsulin": 0.65, 
        "activity": 0.0006, 
        "basaliob": 0.002, 
        "time": "2016-08-09T08:37:33.000Z", 
        "hightempinsulin": 0.65, 
        "bolussnooze": 0, 
        "iob": 0.002
      }, 
      {
        "netbasalinsulin": 0.5, 
        "activity": 0.0003, 
        "basaliob": 0.001, 
        "time": "2016-08-09T08:42:33.000Z", 
        "hightempinsulin": 0.5, 
        "bolussnooze": 0, 
        "iob": 0.001
      }, 
      {
        "netbasalinsulin": 0.3, 
        "activity": 0.0001, 
        "basaliob": 0, 
        "time": "2016-08-09T08:47:33.000Z", 
        "hightempinsulin": 0.3, 
        "bolussnooze": 0, 
        "iob": 0
      }
    ], 
    "enacted": {
      "bg": 119, 
      "temp": "absolute", 
      "snoozeBG": 181, 
      "recieved": true, 
      "predBGs": {
        "COB": [
          119, 
          126, 
          133, 
          140, 
          147, 
          155, 
          162, 
          168, 
          175, 
          181, 
          186, 
          192, 
          196, 
          200, 
          204, 
          207, 
          209, 
          211, 
          213, 
          215, 
          216, 
          217, 
          218, 
          219, 
          220, 
          221, 
          222, 
          223, 
          223, 
          224, 
          225, 
          225, 
          226, 
          226, 
          227
        ], 
        "aCOB": [
          119, 
          128, 
          137, 
          146, 
          155, 
          163, 
          172, 
          180, 
          187, 
          194, 
          201, 
          207, 
          212, 
          217, 
          221, 
          224, 
          227, 
          229, 
          231, 
          232, 
          233, 
          234, 
          235, 
          235, 
          235, 
          235, 
          235, 
          235, 
          234, 
          233, 
          232, 
          231, 
          230, 
          229, 
          229, 
          228
        ], 
        "IOB": [
          119, 
          126, 
          132, 
          137, 
          143, 
          148, 
          152, 
          156, 
          158, 
          160, 
          161, 
          161, 
          160, 
          159, 
          157, 
          155, 
          153, 
          151, 
          148, 
          145, 
          143, 
          140, 
          138, 
          136, 
          133, 
          131, 
          129, 
          127, 
          125, 
          124, 
          122, 
          121, 
          120, 
          119, 
          118, 
          118, 
          117
        ]
      }, 
      "reason": "COB: 33, Dev: 48, BGI: -0.73, ISF: 76.9, Target: 80; Eventual BG 227 >= 80, adj. req. rate: 3.5 to maxSafeBasal: 3.0, temp 2.35<3.0U/hr", 
      "rate": 3, 
      "COB": 33, 
      "eventualBG": 227, 
      "timestamp": "2016-08-09T05:26:12.000Z", 
      "duration": 30, 
      "tick": "+9", 
      "IOB": -0.016
    }
  }, 
  "mmtune": {
    "scanDetails": [
      [
        "916.564", 
        3, 
        -89
      ], 
      [
        "916.588", 
        5, 
        -77
      ], 
      [
        "916.612", 
        4, 
        -90
      ], 
      [
        "916.636", 
        5, 
        -84
      ], 
      [
        "916.660", 
        5, 
        -85
      ], 
      [
        "916.684", 
        5, 
        -87
      ], 
      [
        "916.708", 
        5, 
        -92
      ]
    ], 
    "setFreq": 916.588, 
    "timestamp": "2016-08-09T05:52:23.000Z", 
    "usedDefault": false
  }
}