{
  "device": "openaps://indy-e1", 
  "pump": {
    "battery": {
      "status": "normal", 
      "voltage": 1.57
    }, 
    "status": {
      "status": "normal", 
      "timestamp": "2016-08-28T03:15:20.000Z", 
      "bolusing": false, 
      "suspended": false
    }, 
    "reservoir": 142.125, 
    "clock": "2016-08-27T20:15:16-07:00"
  }, 
  "uploader": {
    "battery": 57, 
    "batteryVoltage": 3746
  }, 
  "openaps": {
    "suggested": {
      "bg": 71, 
      "temp": "absolute", 
      "snoozeBG": 109, 
      "timestamp": "2016-08-28T03:16:45.000Z", 
      "predBGs": {
        "COB": [
          71, 
          73, 
          75, 
          78, 
          82, 
          87, 
          91, 
          97, 
          103, 
          109, 
          116, 
          123, 
          130, 
          138, 
          146, 
          154, 
          162, 
          171, 
          179, 
          188, 
          195, 
          203, 
          210, 
          218, 
          224, 
          231, 
          237, 
          244, 
          250, 
          255, 
          261, 
          266, 
          272, 
          277, 
          282, 
          287, 
          292, 
          297, 
          301, 
          306, 
          310, 
          314, 
          318
        ], 
        "aCOB": [
          71, 
          70, 
          71, 
          71, 
          73, 
          75, 
          78, 
          81, 
          85, 
          90, 
          95, 
          100, 
          106, 
          112, 
          119, 
          125, 
          132, 
          140, 
          147, 
          154, 
          161, 
          168, 
          174, 
          180, 
          186, 
          192, 
          198, 
          204, 
          209, 
          215, 
          220, 
          225, 
          231, 
          236, 
          241, 
          246, 
          251, 
          256, 
          261, 
          265, 
          270, 
          275, 
          279
        ], 
        "IOB": [
          71, 
          72, 
          73, 
          73, 
          74, 
          74, 
          74, 
          73, 
          72, 
          71, 
          70, 
          68, 
          65, 
          63, 
          61, 
          60, 
          59, 
          58, 
          58, 
          58, 
          57, 
          56, 
          56, 
          55, 
          54, 
          54, 
          53, 
          52, 
          51, 
          50, 
          50, 
          49, 
          48, 
          48, 
          47, 
          47, 
          47, 
          46
        ]
      }, 
      "reason": "COB: 75, Dev: 75, BGI: -10.47, ISF: 92, Target: 80; Eventual BG 318 >= 80, temp 1.55 >~ req 1.35U/hr", 
      "COB": 75, 
      "eventualBG": 318, 
      "tick": "+2", 
      "IOB": 0.555
    }, 
    "iob": {
      "netbasalinsulin": -0.8, 
      "timestamp": "2016-08-28T03:15:16.000Z", 
      "activity": 0.0228, 
      "basaliob": -0.399, 
      "hightempinsulin": 0.25, 
      "bolussnooze": 0, 
      "iob": 0.555
    }, 
    "enacted": {
      "bg": 69, 
      "temp": "absolute", 
      "snoozeBG": 117, 
      "recieved": true, 
      "reason": "COB: 76, Dev: 86, BGI: -11.25, ISF: 92, Target: 80; Eventual BG 368 >= 80, temp 0.7<1.55U/hr", 
      "rate": 1.55, 
      "COB": 76, 
      "eventualBG": 368, 
      "timestamp": "2016-08-28T03:11:58.000Z", 
      "duration": 30, 
      "tick": "+3", 
      "IOB": 0.567
    }
  }, 
  "mmtune": {
    "scanDetails": [
      [
        "916.564", 
        5, 
        -72
      ], 
      [
        "916.588", 
        5, 
        -68
      ], 
      [
        "916.612", 
        4, 
        -73
      ], 
      [
        "916.636", 
        4, 
        -73
      ], 
      [
        "916.660", 
        5, 
        -72
      ], 
      [
        "916.684", 
        5, 
        -76
      ], 
      [
        "916.708", 
        5, 
        -85
      ]
    ], 
    "setFreq": 916.588, 
    "timestamp": "2016-08-28T03:14:59.000Z", 
    "usedDefault": false
  }
}